README.rst
setup.py
django_fairepart.egg-info/PKG-INFO
django_fairepart.egg-info/SOURCES.txt
django_fairepart.egg-info/dependency_links.txt
django_fairepart.egg-info/not-zip-safe
django_fairepart.egg-info/pbr.json
django_fairepart.egg-info/requires.txt
django_fairepart.egg-info/top_level.txt
fairepart/__init__.py
fairepart/compat.py
fairepart/exceptions.py
fairepart/forms.py
fairepart/helpers.py
fairepart/models.py
fairepart/settings.py
fairepart/signals.py
fairepart/urls.py
fairepart/utils.py
fairepart/views.py
fairepart/backends/__init__.py
fairepart/backends/base.py
fairepart/backends/facebook.py
fairepart/backends/google.py
fairepart/south_migrations/0001_initial.py
fairepart/south_migrations/0002_auto__add_field_relation_name.py
fairepart/south_migrations/0003_auto__add_invitation.py
fairepart/south_migrations/__init__.py
fairepart/tests/__init__.py
fairepart/tests/models.py
fairepart/tests/settings.py
fairepart/tests/tests.py